setup.py
dsnd_probabilit_Fadi/Binomialdistribution.py
dsnd_probabilit_Fadi/Gaussiandistribution.py
dsnd_probabilit_Fadi/Generaldistribution.py
dsnd_probabilit_Fadi/__init__.py
dsnd_probabilit_Fadi.egg-info/PKG-INFO
dsnd_probabilit_Fadi.egg-info/SOURCES.txt
dsnd_probabilit_Fadi.egg-info/dependency_links.txt
dsnd_probabilit_Fadi.egg-info/not-zip-safe
dsnd_probabilit_Fadi.egg-info/top_level.txt